lookeng/__init__.py
lookeng/lookeng.py
lookeng-0.0.1.dist-info/AUTHORS.rst
lookeng-0.0.1.dist-info/LICENSE
lookeng-0.0.1.dist-info/METADATA
lookeng-0.0.1.dist-info/WHEEL
lookeng-0.0.1.dist-info/top_level.txt
lookeng-0.0.1.dist-info/RECORD
