Metadata-Version: 2.1
Name: lookeng
Version: 0.0.1
Summary: AI Agent for research level Math.
Home-page: https://github.com/RexWzh/lookeng
Author: Rex Wang
Author-email: 1073853456@qq.com
License: MIT license
Keywords: lookeng
Classifier: Development Status :: 2 - Pre-Alpha
Classifier: Intended Audience :: Developers
Classifier: License :: OSI Approved :: MIT License
Classifier: Natural Language :: English
Classifier: Programming Language :: Python :: 3
Classifier: Programming Language :: Python :: 3.6
Classifier: Programming Language :: Python :: 3.7
Classifier: Programming Language :: Python :: 3.8
Requires-Python: >=3.6
License-File: LICENSE
License-File: AUTHORS.rst
